boostpi/__init__.py
boostpi/__main__.py
boostpi/main.py
boostpi-0.1.6.dist-info/entry_points.txt
boostpi-0.1.6.dist-info/WHEEL
boostpi-0.1.6.dist-info/METADATA
boostpi-0.1.6.dist-info/RECORD
